pyxtools/__init__.py
pyxtools/basic_tools/__init__.py
pyxtools/basic_tools/async_http_tool.py
pyxtools/basic_tools/cache_tools.py
pyxtools/basic_tools/email_utils.py
pyxtools/basic_tools/encode_tools.py
pyxtools/basic_tools/file_tools.py
pyxtools/basic_tools/iterator_utils.py
pyxtools/basic_tools/log.py
pyxtools/basic_tools/md5_tools.py
pyxtools/basic_tools/numpy_tools.py
pyxtools/basic_tools/os_tools.py
pyxtools/basic_tools/pprof_tools.py
pyxtools/basic_tools/request_tools.py
pyxtools/basic_tools/singleton_tools.py
pyxtools/basic_tools/socket_tools.py
pyxtools/basic_tools/ws_p2p.py
pyxtools/dev_tools/__init__.py
pyxtools/dev_tools/crlf_tools.py
pyxtools/dev_tools/export_package.py
pyxtools/dev_tools/git_tools.py
pyxtools/faiss_tools/__init__.py
pyxtools/faiss_tools/faiss_utils.py
pyxtools/faiss_tools/search_api.py
pyxtools/faiss_tools/test/3-IVFPQ.py
pyxtools/faiss_tools/test/4-GPU.py
pyxtools/faiss_tools/test/__init__.py
pyxtools/faiss_tools/test/bench.py
pyxtools/faiss_tools/test/faiss_demo.py
pyxtools/faiss_tools/test/test_search_api.py
pyxtools/image_tools/__init__.py
pyxtools/image_tools/cv_utils.py
pyxtools/image_tools/image_utils.py
pyxtools/tmp_tools/__init__.py
pyxtools/tmp_tools/flask_blog.py
pyxtools/tmp_tools/sqlalchemy_demo.py
test/__init__.py
test/test_basic_tools.py
test/test_numpy_tools.py
test/test_sqlalchemy_demo.py
pyxtools-2022.5.28.2.dist-info/LICENSE
pyxtools-2022.5.28.2.dist-info/METADATA
pyxtools-2022.5.28.2.dist-info/WHEEL
pyxtools-2022.5.28.2.dist-info/top_level.txt
pyxtools-2022.5.28.2.dist-info/RECORD
